dfbar/__init__.py
dfbar/__main__.py
dfbar/dfbar.py
dfbar-0.4.4.dist-info/licenses/LICENSE
dfbar-0.4.4.dist-info/METADATA
dfbar-0.4.4.dist-info/WHEEL
dfbar-0.4.4.dist-info/entry_points.txt
dfbar-0.4.4.dist-info/top_level.txt
dfbar-0.4.4.dist-info/RECORD
