Metadata-Version: 2.4
Name: dfbar
Version: 0.4.4
Summary: Dockerfile Build and Run
Home-page: https://github.com/archmachina/dfbar
Download-URL: https://pypi.org/project/dfbar/
Author: Jesse Reichman
License: MIT
Keywords: Dockerfile,Build,Run
License-File: LICENSE
Dynamic: author
Dynamic: description-content-type
Dynamic: download-url
Dynamic: home-page
Dynamic: keywords
Dynamic: license
Dynamic: license-file
Dynamic: summary
